AUTHORS
INSTALL
LICENSE
MANIFEST.in
NOTICE
README
requirements.txt
setup.cfg
setup.py
docs/Makefile
docs/conf.py
docs/configuration.rst
docs/faq.rst
docs/index.rst
docs/installation.rst
docs/introduction.rst
docs/make.bat
docs/usage.rst
src/django_primary_filters.egg-info/PKG-INFO
src/django_primary_filters.egg-info/SOURCES.txt
src/django_primary_filters.egg-info/dependency_links.txt
src/django_primary_filters.egg-info/top_level.txt
src/primary_filters/__init__.py
src/primary_filters/models.py
src/primary_filters/settings.py
src/primary_filters/tests.py
src/primary_filters/utils.py
src/primary_filters/templatetags/__init__.py
src/primary_filters/templatetags/primary_filters_tags.py